tkns/__init__.py
TK_nonlinear_sliding-0.0.1.dist-info/LICENSE.txt
TK_nonlinear_sliding-0.0.1.dist-info/METADATA
TK_nonlinear_sliding-0.0.1.dist-info/WHEEL
TK_nonlinear_sliding-0.0.1.dist-info/top_level.txt
TK_nonlinear_sliding-0.0.1.dist-info/RECORD
