Metadata-Version: 2.1
Name: TK_nonlinear_sliding
Version: 0.0.1
Summary: Implementing nonlinear sliding of tkiner components
Home-page: https://github.com/leletxh/TK-nonlinear-sliding
Author: Liu Zichang
Author-email: 1926341659@qq.com
Classifier: Programming Language :: Python :: 3
Classifier: License :: OSI Approved :: MIT License
Classifier: Operating System :: OS Independent
Requires-Python: >=3.8
License-File: LICENSE.txt
